{"q5wCBoM6Y+2vRVCXSzLaSw==":"giftest.gif","pa5Dkwo/T1qgW/t0h+fQvA==":"background5.jpg","qz/gN6X0RF5XWQAL115GnA==":"mcgif2.gif","FcyH0v2ii/WCo8fnt0JxIg==":"avatar-poboczny-serwera-pieselcraft.png","yRcmXblMbG7nT0zdDqRJpQ==":"serwerownia.jpg","a8c9+DukX+iZmP5U+7yH+g==":"owner.png","pyeMflFIWLHBI3NrUSCpLQ==":"admin-510x510.png","2DrnAMxf2HavyE0E/E346A==":"headadmin-510x603.png","r9VQ88VzXXlCvyXZa+1kew==":"pomocnik-510x510.png","/0jTFPIKv2DdpOc5vXNF6Q==":"mod-240x240.png","bamgKFxywwTksBg1PqDFuQ==":"podserw.gif","VFopm8FAoAVq1cOBg6n+Fg==":"ezgif.com-gif-maker.gif","nEsSq5rmb++7itXo8mw5FQ==":"gif.gif"}